pki/__init__.py
pki/account.py
pki/authority.py
pki/cert.py
pki/client.py
pki/crypto.py
pki/encoder.py
pki/feature.py
pki/info.py
pki/key.py
pki/keyring.py
pki/kra.py
pki/nssdb.py
pki/pkcs12.py
pki/profile.py
pki/system.py
pki/systemcert.py
pki/upgrade.py
pki/util.py
pki/cli/__init__.py
pki/cli/main.py
pki/cli/password.py
pki/cli/pkcs12.py
pki/cli/upgrade.py
dogtag_pki-11.2.1.dist-info/METADATA
dogtag_pki-11.2.1.dist-info/WHEEL
dogtag_pki-11.2.1.dist-info/top_level.txt
dogtag_pki-11.2.1.dist-info/RECORD
