Metadata-Version: 2.1
Name: dogtag-pki
Version: 11.2.1
Summary: Client library for Dogtag Certificate System
Home-page: https://www.dogtagpki.org
Author: Dogtag Certificate System Team
Author-email: devel@lists.dogtagpki.org
License: LGPLv3+
Keywords: pki x509 cert certificate
Classifier: Development Status :: 5 - Production/Stable
Classifier: Environment :: Web Environment
Classifier: Intended Audience :: System Administrators
Classifier: Operating System :: OS Independent
Classifier: Programming Language :: Python :: 3.6
Classifier: Programming Language :: Python :: 3.7
Classifier: Programming Language :: Python :: 3.8
Classifier: Programming Language :: Python :: 3.9
Classifier: Programming Language :: Python :: 3.10
Classifier: Programming Language :: Python :: 3.11
Classifier: License :: OSI Approved :: GNU Lesser General Public License v3 or later (LGPLv3+)
Classifier: Topic :: Security :: Cryptography
Requires-Dist: requests
Requires-Dist: six
Requires-Dist: cryptography
